grappelli_extensions/__init__.py
grappelli_extensions/models.py
grappelli_extensions/navbar.py
grappelli_extensions/nodes.py
grappelli_extensions/static/grappelli_extensions/css/grappelli_extensions.css
grappelli_extensions/templates/admin/includes_grappelli/switch_user_dropdown.html
grappelli_extensions/templates/grappelli/navbar.html
grappelli_extensions/templatetags/__init__.py
grappelli_extensions/templatetags/grappelli_navbar.py
django_grappelli_extensions2-1.0.3.dist-info/METADATA
django_grappelli_extensions2-1.0.3.dist-info/WHEEL
django_grappelli_extensions2-1.0.3.dist-info/top_level.txt
django_grappelli_extensions2-1.0.3.dist-info/RECORD
