Metadata-Version: 2.1
Name: django-grappelli-extensions2
Version: 1.0.3
Summary: Extensions for Grappelli Admin interface
Home-page: http://github.com/django-grappelli-extensions/django-grappelli-extensions
Author: Paulo R. Macedo, Igor P. Leroy
Author-email: proberto.macedo@gmail.com, ip.leroy@gmail.com
License: BSD
Classifier: Development Status :: 5 - Production/Stable
Classifier: Intended Audience :: Developers
Classifier: License :: OSI Approved :: Apache Software License
Classifier: Programming Language :: Python
Classifier: Operating System :: OS Independent
Classifier: Topic :: Software Development :: Libraries
Classifier: Topic :: Utilities
Classifier: Environment :: Web Environment
Classifier: Framework :: Django
Requires-Dist: django
Requires-Dist: django-grappelli
Requires-Dist: django-classy-tags
